README.md
setup.py
src/rdmysql/__init__.py
src/rdmysql/archive.py
src/rdmysql/daily.py
src/rdmysql/database.py
src/rdmysql/expr.py
src/rdmysql/row.py
src/rdmysql/table.py
src/rdmysql.egg-info/PKG-INFO
src/rdmysql.egg-info/SOURCES.txt
src/rdmysql.egg-info/dependency_links.txt
src/rdmysql.egg-info/requires.txt
src/rdmysql.egg-info/top_level.txt