Metadata-Version: 1.1
Name: rdmysql
Version: 0.2.2
Summary: a simple db layer based on ultra-mysql
Home-page: https://github.com/azhai/rdmysql
Author: Ryan Liu
Author-email: azhai@126.com
License: MIT
Keywords: mysql,database,model
Platform: UNKNOWN
Classifier: Development Status :: 5 - Production/Stable
Classifier: Environment :: Web Environment
Classifier: Intended Audience :: Developers
Classifier: Topic :: Database :: Front-Ends
Classifier: License :: OSI Approved :: MIT License
